chinmay_fine/__init__.py
chinmay_fine/fine_calculation.py
chinmay_fine-0.2.dist-info/METADATA
chinmay_fine-0.2.dist-info/WHEEL
chinmay_fine-0.2.dist-info/top_level.txt
chinmay_fine-0.2.dist-info/RECORD
